odoo9_addon_account_fiscal_position_rule_purchase-9.0.1.0.0.99.dev12-py3.8-nspkg.pth
odoo_addons/account_fiscal_position_rule_purchase/README.rst
odoo_addons/account_fiscal_position_rule_purchase/__init__.py
odoo_addons/account_fiscal_position_rule_purchase/__openerp__.py
odoo_addons/account_fiscal_position_rule_purchase/i18n/account_fiscal_position_rule_purchase.pot
odoo_addons/account_fiscal_position_rule_purchase/i18n/de.po
odoo_addons/account_fiscal_position_rule_purchase/i18n/es.po
odoo_addons/account_fiscal_position_rule_purchase/i18n/fi.po
odoo_addons/account_fiscal_position_rule_purchase/i18n/fr.po
odoo_addons/account_fiscal_position_rule_purchase/i18n/fr_FR.po
odoo_addons/account_fiscal_position_rule_purchase/i18n/gl.po
odoo_addons/account_fiscal_position_rule_purchase/i18n/it.po
odoo_addons/account_fiscal_position_rule_purchase/i18n/nl.po
odoo_addons/account_fiscal_position_rule_purchase/i18n/pt_BR.po
odoo_addons/account_fiscal_position_rule_purchase/i18n/ro.po
odoo_addons/account_fiscal_position_rule_purchase/i18n/sl.po
odoo_addons/account_fiscal_position_rule_purchase/i18n/vi_VN.po
odoo_addons/account_fiscal_position_rule_purchase/models/__init__.py
odoo_addons/account_fiscal_position_rule_purchase/models/purchase.py
odoo_addons/account_fiscal_position_rule_purchase/security/ir.model.access.csv
odoo_addons/account_fiscal_position_rule_purchase/static/description/icon.png
odoo_addons/account_fiscal_position_rule_purchase/test/account_fiscal_position_rule_purchase.yml
odoo9_addon_account_fiscal_position_rule_purchase-9.0.1.0.0.99.dev12.dist-info/METADATA
odoo9_addon_account_fiscal_position_rule_purchase-9.0.1.0.0.99.dev12.dist-info/WHEEL
odoo9_addon_account_fiscal_position_rule_purchase-9.0.1.0.0.99.dev12.dist-info/namespace_packages.txt
odoo9_addon_account_fiscal_position_rule_purchase-9.0.1.0.0.99.dev12.dist-info/top_level.txt
odoo9_addon_account_fiscal_position_rule_purchase-9.0.1.0.0.99.dev12.dist-info/RECORD
